setup.py
rest/__init__.py
rest/rest.py
resttweet/__init__.py
resttweet/resttweet.py
restwin/__init__.py
restwin/voiceroid.py
texttoneenc.egg-info/PKG-INFO
texttoneenc.egg-info/SOURCES.txt
texttoneenc.egg-info/dependency_links.txt
texttoneenc.egg-info/top_level.txt