Metadata-Version: 1.0
Name: texttoneenc
Version: 1.3
Summary: Convert dialects and sentences using artificial intelligence.
Home-page: https://osawayuto.ngrok.io/
Author: Osawa Yuto
Author-email: osawa_yuto@yahoo.co.jp
License: -
Platform: UNKNOWN
